package/__init__.py
package/hypermap.py
package/utils.py
hypermap-0.1.1.dist-info/METADATA
hypermap-0.1.1.dist-info/WHEEL
hypermap-0.1.1.dist-info/top_level.txt
hypermap-0.1.1.dist-info/RECORD
